guilt_3p/__init__.py
guilt_3p/config.py
guilt_3p/get_active_windows.py
guilt_3p/main.py
guilt_3p/state.py
guilt_3p/assets/extension/background.js
guilt_3p/assets/extension/manifest.json
guilt_3p/data/__init__.py
guilt_3p/data/browsers.py
guilt_3p/data/forbidden.py
guilt_3p/data/nagging.py
guilt_3p/data/praises.py
guilt_3p/data/roasts.py
guilt_3p/roast_modules/__init__.py
guilt_3p/roast_modules/bring_vscode.py
guilt_3p/roast_modules/log_shame.py
guilt_3p/roast_modules/roaster_speaker.py
guilt_3p/roast_modules/send_nag.py
guilt_3p/utils/__init__.py
guilt_3p/utils/break_input.py
guilt_3p-0.1.0.dist-info/licenses/LICENSE
guilt_3p-0.1.0.dist-info/METADATA
guilt_3p-0.1.0.dist-info/WHEEL
guilt_3p-0.1.0.dist-info/entry_points.txt
guilt_3p-0.1.0.dist-info/top_level.txt
guilt_3p-0.1.0.dist-info/RECORD
