Metadata-Version: 2.4
Name: guilt-3p
Version: 0.1.0
Summary: A CLI productivity tool that roasts you for slacking off.
Author-email: Sudharsan Vanamali <sudharsan.vanamali@gmail.com>
Project-URL: Homepage, https://github.com/Astrasv/guilt-3p
Project-URL: Issues, https://github.com/Astrasv/guilt-3p/issues
Classifier: Programming Language :: Python :: 3
Classifier: License :: OSI Approved :: MIT License
Classifier: Operating System :: Microsoft :: Windows
Requires-Python: >=3.11
License-File: LICENSE
Requires-Dist: flask>=3.1.2
Requires-Dist: flask-cors>=6.0.2
Requires-Dist: gtts>=2.5.4
Requires-Dist: playsound==1.2.2
Requires-Dist: plyer>=2.1.0
Requires-Dist: psutil>=7.2.1
Requires-Dist: pyttsx3>=2.99
Requires-Dist: platformdirs>=4.0.0
Requires-Dist: textual>=0.47.1
Requires-Dist: rich>=13.7.0
Requires-Dist: build>=1.4.0
Requires-Dist: twine>=6.2.0
Dynamic: license-file
